xsource/__init__.py
xsource/api.py
xsource/auth.py
xsource/bench.py
xsource/cli.py
xsource/config.py
xsource/output.py
xsource/report.py
xsource/scan.py
xsource/scanner.py
xsource/utils.py
xsource/vectors/__init__.py
xsource/vectors/baseline_50.py
xsource_cli-0.3.0.dist-info/METADATA
xsource_cli-0.3.0.dist-info/WHEEL
xsource_cli-0.3.0.dist-info/entry_points.txt
xsource_cli-0.3.0.dist-info/RECORD
