Metadata-Version: 2.4
Name: xsource-cli
Version: 0.3.0
Summary: XSource Security CLI - AI Agent Security Scanner (Free Tier: 50 vectors)
Project-URL: Homepage, https://xsourcesec.com
Project-URL: Documentation, https://docs.xsourcesec.com/cli
Project-URL: Repository, https://github.com/XSource-Sec/xsource-cli
Project-URL: Issues, https://github.com/XSource-Sec/xsource-cli/issues
Project-URL: Pricing, https://xsourcesec.com/pricing
Author-email: XSource Security <support@xsourcesec.com>
License-Expression: MIT
Keywords: ai,jailbreak,llm,owasp,prompt-injection,scanning,security
Classifier: Development Status :: 4 - Beta
Classifier: Environment :: Console
Classifier: Intended Audience :: Developers
Classifier: Intended Audience :: System Administrators
Classifier: License :: OSI Approved :: MIT License
Classifier: Operating System :: OS Independent
Classifier: Programming Language :: Python :: 3
Classifier: Programming Language :: Python :: 3.10
Classifier: Programming Language :: Python :: 3.11
Classifier: Programming Language :: Python :: 3.12
Classifier: Topic :: Security
Classifier: Topic :: Software Development :: Testing
Requires-Python: >=3.10
Requires-Dist: httpx>=0.25.0
Requires-Dist: rich>=13.0.0
Requires-Dist: typer[all]>=0.9.0
Provides-Extra: dev
Requires-Dist: black>=23.0.0; extra == 'dev'
Requires-Dist: pytest-asyncio>=0.21.0; extra == 'dev'
Requires-Dist: pytest>=7.0.0; extra == 'dev'
Requires-Dist: ruff>=0.1.0; extra == 'dev'
